lcdtoolbox/Controllers.py
lcdtoolbox/Dynamics.py
lcdtoolbox/Solvers.py
lcdtoolbox/Symbolic.py
lcdtoolbox/TimeResponse.py
lcdtoolbox/TransferFunctions.py
lcdtoolbox/__init__.py
lcdtoolbox/py.typed
LCDToolbox-1.0.0.dist-info/LICENSE
LCDToolbox-1.0.0.dist-info/METADATA
LCDToolbox-1.0.0.dist-info/WHEEL
LCDToolbox-1.0.0.dist-info/top_level.txt
LCDToolbox-1.0.0.dist-info/RECORD
