Metadata-Version: 2.1
Name: LCDToolbox
Version: 1.0.0
Summary: Toolbox for the DTU course: Linear control design - 34721 (Fall 2023)
Author-email: Thomas Hegelund <s211899@dtu.dk>, Long van Ngo <s214606@dtu.dk>, Peter Bonvang <s214658@dtu.dk>
License: MIT License
Project-URL: Homepage, https://github.com/SygesteKIDsPaaBlokken/34721-Toolbox
Project-URL: Issues, https://github.com/SygesteKIDsPaaBlokken/34721-Toolbox/issues
Classifier: Programming Language :: Python :: 3
Classifier: License :: OSI Approved :: MIT License
Classifier: Operating System :: OS Independent
Requires-Python: >=3.11
License-File: LICENSE
Requires-Dist: numpy
Requires-Dist: sympy
Requires-Dist: control
Requires-Dist: matplotlib
